amit26april/__init__.py
amit26april/image_cnn.py
amit26april-0.0.4.dist-info/LICENSE
amit26april-0.0.4.dist-info/METADATA
amit26april-0.0.4.dist-info/WHEEL
amit26april-0.0.4.dist-info/top_level.txt
amit26april-0.0.4.dist-info/RECORD
