Metadata-Version: 2.1
Name: amit26april
Version: 0.0.4
Summary: A libirary to automate developing keras models
Author: Ayush Agrawal
Author-email: aagrawal963@gmail.com
Keywords: experts,begginers,deep learning,ai ultimate,ayush agrawal,automate steps of deep learning,manupliate image dataset,ai less code,ai work companion,basic model develoment,expert kit,ai,tensorflow,keras
Classifier: Development Status :: 1 - Planning
Classifier: Intended Audience :: Developers
Classifier: Programming Language :: Python :: 3
Classifier: Operating System :: Unix
Classifier: Operating System :: MacOS :: MacOS X
Classifier: Operating System :: Microsoft :: Windows
License-File: LICENSE
Requires-Dist: tensorflow
Requires-Dist: keras
Requires-Dist: scikit-learn
Requires-Dist: tqdm
Requires-Dist: seaborn
Requires-Dist: Pillow
